project/__init__.py
JAYNAKARANI-0.0.1.dist-info/LICENCE.txt
JAYNAKARANI-0.0.1.dist-info/METADATA
JAYNAKARANI-0.0.1.dist-info/WHEEL
JAYNAKARANI-0.0.1.dist-info/top_level.txt
JAYNAKARANI-0.0.1.dist-info/RECORD
