Metadata-Version: 2.1
Name: JAYNAKARANI
Version: 0.0.1
Summary: GST VALIDATION
Home-page: 
Author: JAY NAKARANI
Author-email: jaynakarani705@gmail.com
License: MIT
Keywords: gstvalidate
Classifier: Development Status :: 5 - Production/Stable
Classifier: Intended Audience :: Education
Classifier: Operating System :: Microsoft :: Windows :: Windows 10
Classifier: License :: OSI Approved :: MIT License
Classifier: Programming Language :: Python :: 3
License-File: LICENCE.txt
